refiner_cli/__init__.py
refiner_cli/cli.py
refiner_cli-0.0.2.dist-info/LICENSE
refiner_cli-0.0.2.dist-info/METADATA
refiner_cli-0.0.2.dist-info/WHEEL
refiner_cli-0.0.2.dist-info/entry_points.txt
refiner_cli-0.0.2.dist-info/top_level.txt
refiner_cli-0.0.2.dist-info/RECORD
