Metadata-Version: 2.1
Name: refiner-cli
Version: 0.0.2
Summary: Refiner CLI allows you to store text as vectors in Pinecone and then search for similar text. It uses OpenAI to generate embeddings and then uses Pinecone to store and search for similar text.
Author-email: Alex Daro <gmx2267@gmail.com>
Project-URL: Homepage, https://github.com/AI-Refiner/refiner-cli
Classifier: Programming Language :: Python :: 3
Classifier: License :: OSI Approved :: MIT License
Classifier: Operating System :: OS Independent
Requires-Python: >=3.7
License-File: LICENSE
Requires-Dist: refiner
Requires-Dist: click
